sandpiper/__init__.py
sandpiper/__main__.py
sandpiper_saas-1.1.0.dist-info/LICENSE.md
sandpiper_saas-1.1.0.dist-info/METADATA
sandpiper_saas-1.1.0.dist-info/WHEEL
sandpiper_saas-1.1.0.dist-info/entry_points.txt
sandpiper_saas-1.1.0.dist-info/top_level.txt
sandpiper_saas-1.1.0.dist-info/RECORD
