Metadata-Version: 2.1
Name: sandpiper-saas
Version: 1.1.0
Summary: Sandpiper SaaS
Home-page: UNKNOWN
Author: Redwood EDA, LLC
License: UNKNOWN
Keywords: sandpiper tlv tl-verilog verilog rtl hdl compiler
Platform: UNKNOWN
Classifier: License :: OSI Approved :: MIT License
License-File: LICENSE.md
